odoo/addons/pos_reset_search/README.rst
odoo/addons/pos_reset_search/__init__.py
odoo/addons/pos_reset_search/__manifest__.py
odoo/addons/pos_reset_search/i18n/es.po
odoo/addons/pos_reset_search/i18n/pos_reset_search.pot
odoo/addons/pos_reset_search/readme/CONTRIBUTORS.rst
odoo/addons/pos_reset_search/readme/DESCRIPTION.rst
odoo/addons/pos_reset_search/readme/USAGE.rst
odoo/addons/pos_reset_search/static/description/icon.png
odoo/addons/pos_reset_search/static/description/index.html
odoo/addons/pos_reset_search/static/src/js/ProductScreen.js
odoo/addons/pos_reset_search/views/templates.xml
odoo14_addon_pos_reset_search-14.0.1.0.1.dist-info/METADATA
odoo14_addon_pos_reset_search-14.0.1.0.1.dist-info/WHEEL
odoo14_addon_pos_reset_search-14.0.1.0.1.dist-info/top_level.txt
odoo14_addon_pos_reset_search-14.0.1.0.1.dist-info/RECORD
